neurofinder
