Metadata-Version: 1.0
Name: neurofinder
Version: 1.1.0
Summary: evaluate neuron finding algorithms
Home-page: https://github.com/freeman-lab/neurofinder-python
Author: freeman-lab
Author-email: the.freeman.lab@gmail.com
License: MIT
Platform: UNKNOWN
